cerebrus/__init__.py
cerebrus-0.2.dist-info/LICENSE
cerebrus-0.2.dist-info/METADATA
cerebrus-0.2.dist-info/WHEEL
cerebrus-0.2.dist-info/top_level.txt
cerebrus-0.2.dist-info/RECORD
