Metadata-Version: 2.1
Name: cerebrus
Version: 0.2
Summary: cerebrus
Home-page: http://github.com/project-cerebrus
Author: Eris9/Sakurai07
Author-email: blzzardst0rm@gmail.com
License: MIT
Platform: UNKNOWN
